taxoniq_db/__init__.py
taxoniq_db/child_nodes.marisa
taxoniq_db/child_nodes.zstd
taxoniq_db/common_name.marisa
taxoniq_db/common_name.zstd
taxoniq_db/description.marisa
taxoniq_db/description.zstd
taxoniq_db/en_wiki_title.marisa
taxoniq_db/en_wiki_title.zstd
taxoniq_db/scientific_name.marisa
taxoniq_db/scientific_name.zstd
taxoniq_db/sn2taxid.marisa
taxoniq_db/taxa.marisa
taxoniq_db/taxid2refrep.marisa
taxoniq_db/taxid2refrep.zstd
taxoniq_db/taxid2refseq.marisa
taxoniq_db/taxid2refseq.zstd
taxoniq_db/wikidata.marisa
taxoniq_db-2021.3.23.dist-info/METADATA
taxoniq_db-2021.3.23.dist-info/WHEEL
taxoniq_db-2021.3.23.dist-info/top_level.txt
taxoniq_db-2021.3.23.dist-info/RECORD
