Metadata-Version: 2.1
Name: taxoniq-db
Version: 2021.3.23
Summary: Taxoniq index for NCBI Taxonomy database
Home-page: https://github.com/chanzuckerberg/taxoniq
Author: Andrey Kislyuk
Author-email: akislyuk@chanzuckerberg.com
License: MIT License
Platform: UNKNOWN
Requires-Dist: taxoniq-accessions (==2021.3.23)
Requires-Dist: taxoniq-accession-lengths (==2021.3.23)
Requires-Dist: taxoniq-accession-offsets (==2021.3.23)
